dobissapi/__init__.py
dobissapi/dobissapi.py
pydobiss-0.1.56.dist-info/licenses/LICENSE
pydobiss-0.1.56.dist-info/METADATA
pydobiss-0.1.56.dist-info/WHEEL
pydobiss-0.1.56.dist-info/top_level.txt
pydobiss-0.1.56.dist-info/RECORD
