Metadata-Version: 2.4
Name: pydobiss
Version: 0.1.56
Summary: python interface to the dobiss developer api
Home-page: https://github.com/kesteraernoudt/pydobiss
Author: Kester Aernoudt
Author-email: kesteraernoudt@yahoo.com
License: MIT
License-File: LICENSE
Requires-Dist: pyjwt
Requires-Dist: aiohttp
Dynamic: author
Dynamic: author-email
Dynamic: description
Dynamic: description-content-type
Dynamic: home-page
Dynamic: license
Dynamic: license-file
Dynamic: requires-dist
Dynamic: summary
